oxygen_lang/__init__.py
oxygen_lang/oxygen.py
oxygen_lang-1.0.3.dist-info/LICENSE
oxygen_lang-1.0.3.dist-info/WHEEL
oxygen_lang-1.0.3.dist-info/METADATA
oxygen_lang-1.0.3.dist-info/RECORD
