Metadata-Version: 2.1
Name: oxygen_lang
Version: 1.0.3
Summary: A simple and easy to learn programming langague
Author-email: Arjun J <jakkipally@gmail.com>
Requires-Python: >=3.5
Classifier: Programming Language :: Python :: 3
Classifier: License :: OSI Approved :: MIT License
Classifier: Operating System :: OS Independent
Project-URL: Bug Tracker, https://github.com/arjunj132/oxygen/issues
Project-URL: Homepage, https://github.com/arjunj132/oxygen
